knn_tspi/__init__.py
knn_tspi/bootstrap.py
knn_tspi/constants.py
knn_tspi/distances.py
knn_tspi/exceptions.py
knn_tspi/predict.py
knn_tspi/scores.py
knn_tspi/similarity.py
knn_tspi/validation.py
knn_tspi-1.0.1.dist-info/LICENSE.txt
knn_tspi-1.0.1.dist-info/METADATA
knn_tspi-1.0.1.dist-info/WHEEL
knn_tspi-1.0.1.dist-info/RECORD
