Metadata-Version: 2.1
Name: knn-tspi
Version: 1.0.1
Summary: K-Nearest Neighbors Time Series Prediction with Invariances
Home-page: https://pypi.org/project/knn-tspi/
License: MIT
Keywords: time series,forecasting,machine learning
Author: GDalforno
Author-email: gdalforno7@gmail.com
Maintainer: GDalforno
Maintainer-email: gdalforno7@gmail.com
Requires-Python: >=3.10,<4.0
Classifier: Development Status :: 5 - Production/Stable
Classifier: Intended Audience :: Developers
Classifier: License :: OSI Approved :: MIT License
Classifier: Operating System :: Unix
Classifier: Programming Language :: Python :: 3
Classifier: Programming Language :: Python :: 3.10
Classifier: Programming Language :: Python :: 3.11
Classifier: Programming Language :: Python :: 3.12
Classifier: Topic :: Scientific/Engineering :: Artificial Intelligence
Requires-Dist: numpy (>=1.26.4,<2.0.0)
Project-URL: Documentation, https://github.com/GDalforno/KNN-TSPI/blob/main/README.md
Project-URL: Repository, https://github.com/GDalforno/KNN-TSPI
